{
    
    "userRegistration":[
        {
            "firstName": "John",
            "lastName": "Rick",
            "emailaddress": "jrick@qa12212.com",
            "telephoneNumber": 3333332222,
            "password": "testing123",
            "confirmpwd":"testing123"
        },
        {
            "firstName": "Peter",
            "lastName": "Cook",
            "emailaddress": "pcook@q2a1223.com",
            "telephoneNumber": 99029191923,
            "password": "testing456",
            "confirmpwd":"testing456"
        }
    ]
    
}
